bpybb/__init__.py
bpybb/addon.py
bpybb/animate.py
bpybb/collection.py
bpybb/color.py
bpybb/empty.py
bpybb/hdri.py
bpybb/material.py
bpybb/mesh.py
bpybb/modifier.py
bpybb/object.py
bpybb/output.py
bpybb/random.py
bpybb/utils.py
bpybb/version.py
bpybb/world_shader.py
bpy_building_blocks-0.0.24.dist-info/LICENSE
bpy_building_blocks-0.0.24.dist-info/METADATA
bpy_building_blocks-0.0.24.dist-info/WHEEL
bpy_building_blocks-0.0.24.dist-info/top_level.txt
bpy_building_blocks-0.0.24.dist-info/RECORD
