Metadata-Version: 2.1
Name: bpy-building-blocks
Version: 0.0.24
Summary: A collection of helper functions and code used for speeding up Blender 3D Python script development.
Home-page: https://github.com/CGArtPython/bpy_building_blocks
Author: Viktor Stepanov
Author-email: cgartpython@gmail.com
License: MIT
Classifier: License :: OSI Approved :: MIT License
Classifier: Programming Language :: Python :: 3
Classifier: Programming Language :: Python :: 3.9
License-File: LICENSE
